nastran/__init__.py
nastran/analysis.py
nastran/utils.py
nastran/aero/__init__.py
nastran/aero/panels.py
nastran/aero/superpanels.py
nastran/aero/analysis/__init__.py
nastran/aero/analysis/flutter.py
nastran/aero/analysis/panel_flutter.py
nastran/geometry/__init__.py
nastran/geometry/panels.py
nastran/post/__init__.py
nastran/post/common.py
nastran/post/f06.py
nastran/post/flutter.py
nastran/post/modal.py
nastran/post/plots.py
nastran/structures/__init__.py
nastran/structures/bc.py
nastran/structures/composite.py
nastran/structures/material.py
nastran/structures/panel.py
nastran_aeroelasticity-0.2.1.dist-info/LICENSE
nastran_aeroelasticity-0.2.1.dist-info/METADATA
nastran_aeroelasticity-0.2.1.dist-info/WHEEL
nastran_aeroelasticity-0.2.1.dist-info/top_level.txt
nastran_aeroelasticity-0.2.1.dist-info/RECORD
