Metadata-Version: 2.1
Name: nastran-aeroelasticity
Version: 0.2.1
Summary: Some usefull routines for aeroelastic analysis with NASTRAN
Home-page: https://github.com/zuckberj/nastran-aero-flutter
Author: Victor Santos
Author-email: victorsantos@ufmg.br
License: UNKNOWN
Project-URL: Bug Tracker, https://github.com/zuckberj/nastran-aero-flutter/issues
Platform: UNKNOWN
Classifier: Programming Language :: Python :: 3
Classifier: License :: OSI Approved :: MIT License
Classifier: Operating System :: OS Independent
Requires-Python: >=3.7
License-File: LICENSE
Requires-Dist: matplotlib (>=3.1.3)
Requires-Dist: numpy (>=1.18.1)
Requires-Dist: pyNastran (>=1.3.2)
Requires-Dist: pandas (>=1.3)
